pyvicp/__init__.py
pyvicp/error_status_register.py
pyvicp/gpib_bits.py
pyvicp/py.typed
pyvicp/version.py
pyvicp/vicpclient.py
pyvicp-1.1.0.dist-info/AUTHORS
pyvicp-1.1.0.dist-info/LICENSE
pyvicp-1.1.0.dist-info/METADATA
pyvicp-1.1.0.dist-info/WHEEL
pyvicp-1.1.0.dist-info/top_level.txt
pyvicp-1.1.0.dist-info/RECORD
