Metadata-Version: 2.1
Name: pyvicp
Version: 1.1.0
Summary: LeCroy VICP protocol in pure Python
Author: Anthony Cake, Urs Schroffenegger, Bob McNamara
Maintainer-email: Bob McNamara <bobm.vegan@gmail.com>
Project-URL: Homepage, https://github.com/bobmcnamara/pyvicp
Project-URL: Bug Tracker, https://github.com/bobmcnamara/pyvicp/issues
Keywords: VICP
Classifier: Development Status :: 4 - Beta
Classifier: Intended Audience :: Developers
Classifier: Intended Audience :: Science/Research
Classifier: License :: OSI Approved :: GNU Lesser General Public License v2 or later (LGPLv2+)
Classifier: Operating System :: Microsoft :: Windows
Classifier: Operating System :: POSIX :: Linux
Classifier: Operating System :: MacOS :: MacOS X
Classifier: Programming Language :: Python
Classifier: Topic :: Scientific/Engineering :: Interface Engine/Protocol Translator
Classifier: Topic :: Software Development :: Libraries :: Python Modules
Classifier: Programming Language :: Python :: 3.7
Classifier: Programming Language :: Python :: 3.8
Classifier: Programming Language :: Python :: 3.9
Classifier: Programming Language :: Python :: 3.10
Requires-Python: >=3.7
License-File: LICENSE
License-File: AUTHORS
